MANIFEST.in
README.rst
setup.py
simplefileserver.egg-info/PKG-INFO
simplefileserver.egg-info/SOURCES.txt
simplefileserver.egg-info/dependency_links.txt
simplefileserver.egg-info/entry_points.txt
simplefileserver.egg-info/not-zip-safe
simplefileserver.egg-info/requires.txt
simplefileserver.egg-info/top_level.txt
src/__init__.py
src/server_side.py
src/templates/index.html